{
  "generator-jhipster": {
    "applicationIndex": 0,
    "applicationType": "gateway",
    "applications": {
      "customerManagement": {
        "applicationIndex": 1,
        "clientFramework": "no",
        "serverPort": "8081"
      }
    },
    "authenticationType": "oauth2",
    "baseName": "gateway",
    "blueprints": [],
    "buildTool": "maven",
    "cacheProvider": "no",
    "clientFramework": "react",
    "clientPackageManager": "npm",
    "clientTheme": "none",
    "clientThemeVariant": "",
    "creationTimestamp": 1671209871652,
    "databaseType": "sql",
    "devDatabaseType": "h2Disk",
    "devServerPort": 9060,
    "dtoSuffix": "DTO",
    "enableGradleEnterprise": false,
    "enableHibernateCache": false,
    "enableSwaggerCodegen": false,
    "enableTranslation": true,
    "entities": ["Vehicle", "Customer"],
    "entitySuffix": "",
    "gradleEnterpriseHost": "",
    "jhiPrefix": "jhi",
    "jhipsterVersion": "7.9.3",
    "jwtSecretKey": "OWJmOTdjYzY1MWJmYmM3NDQwZDU1NzRhOWYyNzUzOWVjNzg0NWU2NDUzNzk5Njg4NTcyZTIwYzE3NjI4ZjEyMTRiZmM1Nzc2NTk3YjQyYjM2MWJkZGVmZGZiMmFkYmQ2Yzg3Yzk4Zjg4YzQ4NzA4Y2UxOGVlN2MyOTMwYTQ0N2Q=",
    "languages": ["en", "ar-ly"],
    "lastLiquibaseTimestamp": 1671209991000,
    "messageBroker": "kafka",
    "nativeLanguage": "en",
    "otherModules": [],
    "packageFolder": "com/ahmedmeid/fleet",
    "packageName": "com.ahmedmeid.fleet",
    "pages": [],
    "prodDatabaseType": "postgresql",
    "reactive": true,
    "searchEngine": false,
    "serverPort": "8080",
    "serviceDiscoveryType": "consul",
    "skipCheckLengthOfIdentifier": false,
    "skipClient": false,
    "skipFakeData": false,
    "skipUserManagement": true,
    "testFrameworks": ["cypress"],
    "websocket": false,
    "withAdminUi": true
  }
}
